skill_stock/LICENSE
skill_stock/LICENSE.md
skill_stock/README.md
skill_stock/__init__.py
skill_stock/skill.json
skill_stock/version.py
skill_stock/locale/ca-es/dialog/api.error.dialog
skill_stock/locale/ca-es/dialog/not.found.dialog
skill_stock/locale/ca-es/dialog/stock.price.dialog
skill_stock/locale/ca-es/regex/company.rx
skill_stock/locale/de-de/dialog/api.error.dialog
skill_stock/locale/de-de/dialog/not.found.dialog
skill_stock/locale/de-de/dialog/stock.price.dialog
skill_stock/locale/de-de/regex/company.rx
skill_stock/locale/el-gr/dialog/not.found.dialog
skill_stock/locale/el-gr/dialog/stock.price.dialog
skill_stock/locale/el-gr/regex/company.rx
skill_stock/locale/en-us/dialog/api.error.dialog
skill_stock/locale/en-us/dialog/not.found.dialog
skill_stock/locale/en-us/dialog/stock.price.dialog
skill_stock/locale/en-us/intent/stock_price.intent
skill_stock/locale/en-us/regex/company.rx
skill_stock/locale/es-es/dialog/api.error.dialog
skill_stock/locale/es-es/dialog/not.found.dialog
skill_stock/locale/es-es/dialog/stock.price.dialog
skill_stock/locale/es-es/regex/company.rx
skill_stock/locale/fr-fr/dialog/api.error.dialog
skill_stock/locale/fr-fr/dialog/not.found.dialog
skill_stock/locale/fr-fr/dialog/stock.price.dialog
skill_stock/locale/fr-fr/regex/company.rx
skill_stock/locale/gl-es/dialog/api.error.dialog
skill_stock/locale/gl-es/dialog/not.found.dialog
skill_stock/locale/gl-es/dialog/stock.price.dialog
skill_stock/locale/gl-es/regex/company.rx
skill_stock/locale/hu-hu/dialog/not.found.dialog
skill_stock/locale/hu-hu/dialog/stock.price.dialog
skill_stock/locale/hu-hu/regex/company.rx
skill_stock/locale/it-it/dialog/api.error.dialog
skill_stock/locale/it-it/dialog/not.found.dialog
skill_stock/locale/it-it/dialog/stock.price.dialog
skill_stock/locale/it-it/regex/company.rx
skill_stock/locale/nl-nl/dialog/api.error.dialog
skill_stock/locale/nl-nl/dialog/not.found.dialog
skill_stock/locale/nl-nl/dialog/stock.price.dialog
skill_stock/locale/nl-nl/regex/company.rx
skill_stock/neon_skill_stock.egg-info/PKG-INFO
skill_stock/neon_skill_stock.egg-info/SOURCES.txt
skill_stock/neon_skill_stock.egg-info/dependency_links.txt
skill_stock/neon_skill_stock.egg-info/entry_points.txt
skill_stock/neon_skill_stock.egg-info/requires.txt
skill_stock/neon_skill_stock.egg-info/top_level.txt
neon_skill_stock-2.0.0.dist-info/LICENSE
neon_skill_stock-2.0.0.dist-info/LICENSE.md
neon_skill_stock-2.0.0.dist-info/METADATA
neon_skill_stock-2.0.0.dist-info/WHEEL
neon_skill_stock-2.0.0.dist-info/entry_points.txt
neon_skill_stock-2.0.0.dist-info/top_level.txt
neon_skill_stock-2.0.0.dist-info/RECORD
